darkgraylib/__init__.py
darkgraylib/argparse_helpers.py
darkgraylib/command_line.py
darkgraylib/config.py
darkgraylib/diff.py
darkgraylib/files.py
darkgraylib/git.py
darkgraylib/help.py
darkgraylib/log.py
darkgraylib/main.py
darkgraylib/plugins.py
darkgraylib/py.typed
darkgraylib/utils.py
darkgraylib/version.py
darkgraylib/highlighting/__init__.py
darkgraylib/highlighting/lexers.py
darkgraylib/tests/test_argparse_helpers.py
darkgraylib/tests/test_command_line.py
darkgraylib/tests/test_config.py
darkgraylib/tests/test_diff.py
darkgraylib/tests/test_files.py
darkgraylib/tests/test_git.py
darkgraylib/tests/test_highlighting.py
darkgraylib/tests/test_main.py
darkgraylib/tests/test_plugins.py
darkgraylib/tests/test_utils.py
darkgraylib/testtools/__init__.py
darkgraylib/testtools/clear_black_cache_plugin.py
darkgraylib/testtools/diff_helpers.py
darkgraylib/testtools/git_repo_plugin.py
darkgraylib/testtools/helpers.py
darkgraylib/testtools/highlighting_helpers.py
darkgraylib/testtools/mock_argument_parser.py
darkgraylib/testtools/patching.py
darkgraylib/testtools/temp_copy.py
darkgraylib-2.4.0.dist-info/licenses/LICENSE
darkgraylib-2.4.0.dist-info/METADATA
darkgraylib-2.4.0.dist-info/WHEEL
darkgraylib-2.4.0.dist-info/entry_points.txt
darkgraylib-2.4.0.dist-info/top_level.txt
darkgraylib-2.4.0.dist-info/RECORD
