Metadata-Version: 2.4
Name: darkgraylib
Version: 2.4.0
Summary: Common supporting code for Darker and Graylint
Author-email: Antti Kaihola <13725+akaihola@users.noreply.github.com>
License: BSD-3-Clause
Project-URL: Homepage, https://github.com/akaihola/darkgraylib
Project-URL: Source Code, https://github.com/akaihola/darkgraylib
Project-URL: Change Log, https://github.com/akaihola/darkgraylib/blob/main/CHANGES.rst
Project-URL: News, https://github.com/akaihola/darkgraylib/discussions/categories/announcements
Classifier: Programming Language :: Python :: 3 :: Only
Classifier: Programming Language :: Python :: 3.9
Classifier: Programming Language :: Python :: 3.10
Classifier: Programming Language :: Python :: 3.11
Classifier: Programming Language :: Python :: 3.12
Classifier: Programming Language :: Python :: 3.13
Requires-Python: >=3.9
License-File: LICENSE
Requires-Dist: toml>=0.10.0
Provides-Extra: color
Requires-Dist: Pygments>=2.4.0; extra == "color"
Dynamic: description
Dynamic: description-content-type
Dynamic: license-file
